delpinos/__init__.py
delpinos/base.py
delpinos_base-0.0.1.dev3.dist-info/LICENSE
delpinos_base-0.0.1.dev3.dist-info/METADATA
delpinos_base-0.0.1.dev3.dist-info/WHEEL
delpinos_base-0.0.1.dev3.dist-info/top_level.txt
delpinos_base-0.0.1.dev3.dist-info/RECORD
