Metadata-Version: 2.1
Name: delpinos-base
Version: 0.0.1.dev3
Summary: Base codes for creating python modules
Author-email: Alef Bruno Delpino de Oliveira <alef@gmail.com>
License: MIT License
Project-URL: Bug Tracker, https://github.com/delpinos/python-base/issues
Project-URL: Homepage, https://github.com/delpinos/python-base
Keywords: base,template,lib
Classifier: Environment :: Console
Classifier: License :: OSI Approved :: MIT License
Classifier: Operating System :: OS Independent
Classifier: Programming Language :: Python :: 3
Classifier: Programming Language :: Python :: 3.9
Classifier: Programming Language :: Python :: 3.10
Classifier: Topic :: Software Development :: Libraries :: Python Modules
Requires-Python: >=3.6
License-File: LICENSE
